{"00":{"FlightDetails":{"Details":[[{"Origin":{"AirportCode":"DLA","CityName":"Douala","AirportName":"Douala","DateTime":"2022-04-12 07:55","FDTV":1649557500},"Destination":{"AirportCode":"ABJ","CityName":"Abidjan","AirportName":"Abidjan","DateTime":"2022-04-12 12:00","FATV":1649572200},"OperatorCode":"HF","DisplayOperatorCode":"","ValidatingAirline":"","OperatorName":"Air cote d'ivoire","FlightNumber":"807","CabinClass":"ECONOMY","Operatedbyairline":null,"Operatedbyairlinename":null,"Duration":465,"Attr":{"Baggage":"40KG","CabinBaggage":null},"stop_over":""},{"Origin":{"AirportCode":"ABJ","CityName":"Abidjan","AirportName":"Abidjan","DateTime":"2022-04-12 20:35","FDTV":1649603100},"Destination":{"AirportCode":"NSI","CityName":"Yaounde","AirportName":"Yaounde","DateTime":"2022-04-13 00:15","FATV":1649529900},"OperatorCode":"HF","DisplayOperatorCode":"","ValidatingAirline":"","OperatorName":"Air cote d'ivoire","FlightNumber":"802","CabinClass":"ECONOMY","Operatedbyairline":null,"Operatedbyairlinename":null,"Duration":465,"Attr":{"Baggage":"40KG","CabinBaggage":null},"stop_over":""}]]},"Price":{"Currency":"USD","TotalDisplayFare":803.061,"PriceBreakup":{"BasicFare":450.161,"Tax":352.9,"AgentCommission":0,"AgentTdsOnCommision":0},"PassengerBreakup":{"ADT":{"BasePrice":450.161,"Tax":352.9,"TotalPrice":803.061,"PassengerCount":"1"}}},"Attr":{"IsRefundable":"","AirlineRemark":"","API":"PK Fare"},"ResultToken":"27b0e98990e0ccca132dedd064973ac6*_*1*_*k0cqN1WEAdydPu9e","api_original_price_details":{"TotalDisplayFare":803.061,"api_currency":"USD","AgentCommission":0,"BasicFare":450.161,"Tax":352.9},"FareDetails":{"Currency":"EUR","BaseFare":409.65,"Tax":321.14,"PublishedFare":730.79,"AgentCommission":0,"AgentTdsOnCommision":0,"OfferedFare":730.79},"PassengerFareBreakdown":{"ADT":{"Tax":352.9,"TotalPrice":803.061,"PassengerCount":"1","BaseFare":409.65}}},"01":{"FlightDetails":{"Details":[[{"Origin":{"AirportCode":"DLA","CityName":"Douala","AirportName":"Douala","DateTime":"2022-04-12 07:55:00","FDTV":1649557500},"Destination":{"AirportCode":"ABJ","CityName":"Abidjan","AirportName":"Abidjan","DateTime":"2022-04-12 12:00:00","FATV":1649572200},"OperatorCode":"HF","DisplayOperatorCode":"","ValidatingAirline":"HR","OperatorName":"Air C\u00f4te d'Ivoire","FlightNumber":"807","CabinClass":"K","Operatedbyairline":"","Operatedbyairlinename":"","Duration":305,"Attr":{"Baggage":"40 KG","CabinBaggage":"7 Kg","AvailableSeats":9},"stop_over":"This Flight has a technical stop at ABV 0 hour 40 minutes"},{"Origin":{"AirportCode":"ABJ","CityName":"Abidjan","AirportName":"Abidjan","DateTime":"2022-04-12 20:35:00","FDTV":1649603100},"Destination":{"AirportCode":"NSI","CityName":"Yaounde","AirportName":"Yaounde","DateTime":"2022-04-13 00:15:00","FATV":1649529900},"OperatorCode":"HF","DisplayOperatorCode":"","ValidatingAirline":"HR","OperatorName":"Air C\u00f4te d'Ivoire","FlightNumber":"802","CabinClass":"K","Operatedbyairline":"","Operatedbyairlinename":"","Duration":160,"AccumulatedDuration":980,"Attr":{"Baggage":"40 KG","CabinBaggage":"7 Kg","AvailableSeats":9},"stop_over":""}]]},"Price":{"Currency":"USD","TotalDisplayFare":839.066,"PriceBreakup":{"BasicFare":446.94,"Tax":392.126,"AgentCommission":0,"AgentTdsOnCommision":0},"PassengerBreakup":{"ADT":{"BasePrice":446.94,"Tax":392.126,"TotalPrice":839.066,"PassengerCount":1}}},"ResultToken":"27b0e98990e0ccca132dedd064973ac6*_*2*_*rYY6rVYSmu79oH0d","Attr":{"IsRefundable":true,"AirlineRemark":"Regular Fare","IsLCC":false},"api_original_price_details":{"TotalDisplayFare":839.066,"api_currency":"USD","AgentCommission":0,"BasicFare":446.94,"Tax":392.126},"FareDetails":{"Currency":"EUR","BaseFare":406.72,"Tax":356.83,"PublishedFare":763.55,"AgentCommission":0,"AgentTdsOnCommision":0,"OfferedFare":763.55},"PassengerFareBreakdown":{"ADT":{"Tax":392.126,"TotalPrice":839.066,"PassengerCount":1,"BaseFare":406.72}}},"02":{"FlightDetails":{"Details":[[{"Origin":{"AirportCode":"DLA","CityName":"Douala","AirportName":"Douala","DateTime":"2022-04-12 10:55:00","FDTV":1649568300},"Destination":{"AirportCode":"LFW","CityName":"Lome","AirportName":"Lome","DateTime":"2022-04-12 11:40:00","FATV":1649571000},"OperatorCode":"KP","DisplayOperatorCode":"","ValidatingAirline":"GP","OperatorName":"ASKY","FlightNumber":"35","CabinClass":"L","Operatedbyairline":"","Operatedbyairlinename":"","Duration":105,"Attr":{"Baggage":"40 KG","CabinBaggage":"7 Kg","AvailableSeats":9},"stop_over":""},{"Origin":{"AirportCode":"LFW","CityName":"Lome","AirportName":"Lome","DateTime":"2022-04-12 13:50:00","FDTV":1649578800},"Destination":{"AirportCode":"NSI","CityName":"Yaounde","AirportName":"Yaounde","DateTime":"2022-04-12 18:45:00","FATV":1649596500},"OperatorCode":"ET","DisplayOperatorCode":"","ValidatingAirline":"GP","OperatorName":"Ethiopian Airlines S C","FlightNumber":"1007","CabinClass":"K","Operatedbyairline":"KP","Operatedbyairlinename":"","Duration":235,"AccumulatedDuration":470,"Attr":{"Baggage":"40 KG","CabinBaggage":"7 Kg","AvailableSeats":7},"stop_over":"This Flight has a technical stop at ABV 0 hour 40 minutes"}]]},"Price":{"Currency":"USD","TotalDisplayFare":1057.012,"PriceBreakup":{"BasicFare":698.281,"Tax":358.73,"AgentCommission":0,"AgentTdsOnCommision":0},"PassengerBreakup":{"ADT":{"BasePrice":698.281,"Tax":358.73,"TotalPrice":1057.012,"PassengerCount":1}}},"ResultToken":"27b0e98990e0ccca132dedd064973ac6*_*3*_*0uI9zk68wez22jKc","Attr":{"IsRefundable":true,"AirlineRemark":"Regular Fare","IsLCC":false},"api_original_price_details":{"TotalDisplayFare":1057.012,"api_currency":"USD","AgentCommission":0,"BasicFare":698.281,"Tax":358.73},"FareDetails":{"Currency":"EUR","BaseFare":635.44,"Tax":326.44,"PublishedFare":961.88,"AgentCommission":0,"AgentTdsOnCommision":0,"OfferedFare":961.88},"PassengerFareBreakdown":{"ADT":{"Tax":358.73,"TotalPrice":1057.012,"PassengerCount":1,"BaseFare":635.44}}},"03":{"FlightDetails":{"Details":[[{"Origin":{"AirportCode":"DLA","CityName":"Douala","AirportName":"Douala","DateTime":"2022-04-12 10:55:00","FDTV":1649568300},"Destination":{"AirportCode":"LFW","CityName":"Lome","AirportName":"Lome","DateTime":"2022-04-12 11:40:00","FATV":1649571000},"OperatorCode":"ET","DisplayOperatorCode":"","ValidatingAirline":"ET","OperatorName":"Ethiopian Airlines S C","FlightNumber":"1035","CabinClass":"L","Operatedbyairline":"KP","Operatedbyairlinename":"","Duration":105,"Attr":{"Baggage":"40 KG","CabinBaggage":"7 Kg","AvailableSeats":7},"stop_over":""},{"Origin":{"AirportCode":"LFW","CityName":"Lome","AirportName":"Lome","DateTime":"2022-04-12 13:50:00","FDTV":1649578800},"Destination":{"AirportCode":"NSI","CityName":"Yaounde","AirportName":"Yaounde","DateTime":"2022-04-12 18:45:00","FATV":1649596500},"OperatorCode":"ET","DisplayOperatorCode":"","ValidatingAirline":"ET","OperatorName":"Ethiopian Airlines S C","FlightNumber":"1007","CabinClass":"K","Operatedbyairline":"KP","Operatedbyairlinename":"","Duration":235,"AccumulatedDuration":470,"Attr":{"Baggage":"40 KG","CabinBaggage":"7 Kg","AvailableSeats":7},"stop_over":"This Flight has a technical stop at ABV 0 hour 40 minutes"}]]},"Price":{"Currency":"USD","TotalDisplayFare":1061.472,"PriceBreakup":{"BasicFare":705.79,"Tax":355.682,"AgentCommission":0,"AgentTdsOnCommision":0},"PassengerBreakup":{"ADT":{"BasePrice":705.79,"Tax":355.682,"TotalPrice":1061.472,"PassengerCount":1}}},"ResultToken":"27b0e98990e0ccca132dedd064973ac6*_*4*_*qLeIT0Ndw5jPkkCs","Attr":{"IsRefundable":true,"AirlineRemark":"Regular Fare","IsLCC":false},"api_original_price_details":{"TotalDisplayFare":1061.472,"api_currency":"USD","AgentCommission":0,"BasicFare":705.79,"Tax":355.682},"FareDetails":{"Currency":"EUR","BaseFare":642.27,"Tax":323.67,"PublishedFare":965.94,"AgentCommission":0,"AgentTdsOnCommision":0,"OfferedFare":965.94},"PassengerFareBreakdown":{"ADT":{"Tax":355.682,"TotalPrice":1061.472,"PassengerCount":1,"BaseFare":642.27}}},"04":{"FlightDetails":{"Details":[[{"Origin":{"AirportCode":"DLA","CityName":"Douala","AirportName":"Douala","DateTime":"2022-04-12 10:55","FDTV":1649568300},"Destination":{"AirportCode":"LFW","CityName":"Lome","AirportName":"Lome","DateTime":"2022-04-12 11:40","FATV":1649571000},"OperatorCode":"ET","DisplayOperatorCode":"","ValidatingAirline":"","OperatorName":"Ethiopian airlines","FlightNumber":"1035","CabinClass":"ECONOMY","Operatedbyairline":null,"Operatedbyairlinename":null,"Duration":300,"Attr":{"Baggage":null,"CabinBaggage":null},"stop_over":""},{"Origin":{"AirportCode":"LFW","CityName":"Lome","AirportName":"Lome","DateTime":"2022-04-12 13:50","FDTV":1649578800},"Destination":{"AirportCode":"ABV","CityName":"Abuja","AirportName":"Abuja","DateTime":"2022-04-12 16:30","FATV":1649588400},"OperatorCode":"ET","DisplayOperatorCode":"","ValidatingAirline":"","OperatorName":"Ethiopian airlines","FlightNumber":"1007","CabinClass":"ECONOMY","Operatedbyairline":null,"Operatedbyairlinename":null,"Duration":300,"Attr":{"Baggage":null,"CabinBaggage":null},"stop_over":""},{"Origin":{"AirportCode":"ABV","CityName":"Abuja","AirportName":"Abuja","DateTime":"2022-04-12 17:10","FDTV":1649590800},"Destination":{"AirportCode":"NSI","CityName":"Yaounde","AirportName":"Yaounde","DateTime":"2022-04-12 18:45","FATV":1649596500},"OperatorCode":"ET","DisplayOperatorCode":"","ValidatingAirline":"","OperatorName":"Ethiopian airlines","FlightNumber":"1007","CabinClass":"ECONOMY","Operatedbyairline":null,"Operatedbyairlinename":null,"Duration":300,"Attr":{"Baggage":null,"CabinBaggage":null},"stop_over":""}]]},"Price":{"Currency":"USD","TotalDisplayFare":1121.271,"PriceBreakup":{"BasicFare":386.84,"Tax":734.431,"AgentCommission":0,"AgentTdsOnCommision":0},"PassengerBreakup":{"ADT":{"BasePrice":386.84,"Tax":734.431,"TotalPrice":1121.271,"PassengerCount":"1"}}},"Attr":{"IsRefundable":"","AirlineRemark":"","API":"PK Fare"},"ResultToken":"27b0e98990e0ccca132dedd064973ac6*_*5*_*G4K7Ld2BtB4FWtev","api_original_price_details":{"TotalDisplayFare":1121.271,"api_currency":"USD","AgentCommission":0,"BasicFare":386.84,"Tax":734.431},"FareDetails":{"Currency":"EUR","BaseFare":352.02,"Tax":668.33,"PublishedFare":1020.36,"AgentCommission":0,"AgentTdsOnCommision":0,"OfferedFare":1020.36},"PassengerFareBreakdown":{"ADT":{"Tax":734.431,"TotalPrice":1121.271,"PassengerCount":"1","BaseFare":352.02}}},"05":{"FlightDetails":{"Details":[[{"Origin":{"AirportCode":"DLA","CityName":"Douala","AirportName":"Douala","DateTime":"2022-04-12 10:55","FDTV":1649568300},"Destination":{"AirportCode":"LFW","CityName":"Lome","AirportName":"Lome","DateTime":"2022-04-12 11:40","FATV":1649571000},"OperatorCode":"KP","DisplayOperatorCode":"","ValidatingAirline":"","OperatorName":"","FlightNumber":"35","CabinClass":"ECONOMY","Operatedbyairline":null,"Operatedbyairlinename":null,"Duration":340,"Attr":{"Baggage":"40KG","CabinBaggage":null},"stop_over":""},{"Origin":{"AirportCode":"LFW","CityName":"Lome","AirportName":"Lome","DateTime":"2022-04-12 13:50","FDTV":1649578800},"Destination":{"AirportCode":"NSI","CityName":"Yaounde","AirportName":"Yaounde","DateTime":"2022-04-12 18:45","FATV":1649596500},"OperatorCode":"KP","DisplayOperatorCode":"","ValidatingAirline":"","OperatorName":"","FlightNumber":"30","CabinClass":"ECONOMY","Operatedbyairline":null,"Operatedbyairlinename":null,"Duration":340,"Attr":{"Baggage":"40KG","CabinBaggage":null},"stop_over":""}]]},"Price":{"Currency":"USD","TotalDisplayFare":1173.161,"PriceBreakup":{"BasicFare":824.161,"Tax":349,"AgentCommission":0,"AgentTdsOnCommision":0},"PassengerBreakup":{"ADT":{"BasePrice":824.161,"Tax":349,"TotalPrice":1173.161,"PassengerCount":"1"}}},"Attr":{"IsRefundable":"","AirlineRemark":"","API":"PK Fare"},"ResultToken":"27b0e98990e0ccca132dedd064973ac6*_*6*_*pWR94E3dn9TZ7CE0","api_original_price_details":{"TotalDisplayFare":1173.161,"api_currency":"USD","AgentCommission":0,"BasicFare":824.161,"Tax":349},"FareDetails":{"Currency":"EUR","BaseFare":749.99,"Tax":317.59,"PublishedFare":1067.58,"AgentCommission":0,"AgentTdsOnCommision":0,"OfferedFare":1067.58},"PassengerFareBreakdown":{"ADT":{"Tax":349,"TotalPrice":1173.161,"PassengerCount":"1","BaseFare":749.99}}},"06":{"FlightDetails":{"Details":[[{"Origin":{"AirportCode":"DLA","CityName":"Douala","AirportName":"Douala","DateTime":"2022-04-12 10:55:00","FDTV":1649568300},"Destination":{"AirportCode":"LFW","CityName":"Lome","AirportName":"Lome","DateTime":"2022-04-12 11:40:00","FATV":1649571000},"OperatorCode":"KP","DisplayOperatorCode":"","ValidatingAirline":"HR","OperatorName":"ASKY","FlightNumber":"35","CabinClass":"V","Operatedbyairline":"","Operatedbyairlinename":"","Duration":105,"Attr":{"Baggage":"40 KG","CabinBaggage":"7 Kg","AvailableSeats":9},"stop_over":""},{"Origin":{"AirportCode":"LFW","CityName":"Lome","AirportName":"Lome","DateTime":"2022-04-12 13:50:00","FDTV":1649578800},"Destination":{"AirportCode":"NSI","CityName":"Yaounde","AirportName":"Yaounde","DateTime":"2022-04-12 18:45:00","FATV":1649596500},"OperatorCode":"KP","DisplayOperatorCode":"","ValidatingAirline":"HR","OperatorName":"ASKY","FlightNumber":"30","CabinClass":"Y","Operatedbyairline":"","Operatedbyairlinename":"","Duration":235,"AccumulatedDuration":470,"Attr":{"Baggage":"40 KG","CabinBaggage":"7 Kg","AvailableSeats":9},"stop_over":"This Flight has a technical stop at ABV 0 hour 40 minutes"}]]},"Price":{"Currency":"USD","TotalDisplayFare":1176.341,"PriceBreakup":{"BasicFare":822.678,"Tax":353.664,"AgentCommission":0,"AgentTdsOnCommision":0},"PassengerBreakup":{"ADT":{"BasePrice":822.678,"Tax":353.664,"TotalPrice":1176.341,"PassengerCount":1}}},"ResultToken":"27b0e98990e0ccca132dedd064973ac6*_*7*_*CFJTEISP0mxJxNyB","Attr":{"IsRefundable":true,"AirlineRemark":"Regular Fare","IsLCC":false},"api_original_price_details":{"TotalDisplayFare":1176.341,"api_currency":"USD","AgentCommission":0,"BasicFare":822.678,"Tax":353.664},"FareDetails":{"Currency":"EUR","BaseFare":748.64,"Tax":321.83,"PublishedFare":1070.47,"AgentCommission":0,"AgentTdsOnCommision":0,"OfferedFare":1070.47},"PassengerFareBreakdown":{"ADT":{"Tax":353.664,"TotalPrice":1176.341,"PassengerCount":1,"BaseFare":748.64}}},"07":{"FlightDetails":{"Details":[[{"Origin":{"AirportCode":"DLA","CityName":"Douala","AirportName":"Douala","DateTime":"2022-04-12 10:55:00","FDTV":1649568300},"Destination":{"AirportCode":"LFW","CityName":"Lome","AirportName":"Lome","DateTime":"2022-04-12 11:40:00","FATV":1649571000},"OperatorCode":"ET","DisplayOperatorCode":"","ValidatingAirline":"ET","OperatorName":"Ethiopian Airlines S C","FlightNumber":"1035","CabinClass":"V","Operatedbyairline":"KP","Operatedbyairlinename":"","Duration":105,"Attr":{"Baggage":"40 KG","CabinBaggage":"7 Kg","AvailableSeats":7},"stop_over":""},{"Origin":{"AirportCode":"LFW","CityName":"Lome","AirportName":"Lome","DateTime":"2022-04-12 13:50:00","FDTV":1649578800},"Destination":{"AirportCode":"NSI","CityName":"Yaounde","AirportName":"Yaounde","DateTime":"2022-04-12 18:45:00","FATV":1649596500},"OperatorCode":"KP","DisplayOperatorCode":"","ValidatingAirline":"ET","OperatorName":"ASKY","FlightNumber":"30","CabinClass":"Y","Operatedbyairline":"","Operatedbyairlinename":"","Duration":235,"AccumulatedDuration":470,"Attr":{"Baggage":"40 KG","CabinBaggage":"7 Kg","AvailableSeats":9},"stop_over":"This Flight has a technical stop at ABV 0 hour 40 minutes"}]]},"Price":{"Currency":"USD","TotalDisplayFare":1207.696,"PriceBreakup":{"BasicFare":848.965,"Tax":358.73,"AgentCommission":0,"AgentTdsOnCommision":0},"PassengerBreakup":{"ADT":{"BasePrice":848.965,"Tax":358.73,"TotalPrice":1207.696,"PassengerCount":1}}},"ResultToken":"27b0e98990e0ccca132dedd064973ac6*_*8*_*L5OQomoWGK2hxDwV","Attr":{"IsRefundable":true,"AirlineRemark":"Regular Fare","IsLCC":false},"api_original_price_details":{"TotalDisplayFare":1207.696,"api_currency":"USD","AgentCommission":0,"BasicFare":848.965,"Tax":358.73},"FareDetails":{"Currency":"EUR","BaseFare":772.56,"Tax":326.44,"PublishedFare":1099,"AgentCommission":0,"AgentTdsOnCommision":0,"OfferedFare":1099},"PassengerFareBreakdown":{"ADT":{"Tax":358.73,"TotalPrice":1207.696,"PassengerCount":1,"BaseFare":772.56}}},"08":{"FlightDetails":{"Details":[[{"Origin":{"AirportCode":"DLA","CityName":"Douala","AirportName":"Douala","DateTime":"2022-04-12 17:20","FDTV":1649591400},"Destination":{"AirportCode":"NDJ","CityName":"Ndjamena","AirportName":"Ndjamena","DateTime":"2022-04-12 19:10","FATV":1649598000},"OperatorCode":"ET","DisplayOperatorCode":"","ValidatingAirline":"","OperatorName":"Ethiopian airlines","FlightNumber":"1011","CabinClass":"ECONOMY","Operatedbyairline":null,"Operatedbyairlinename":null,"Duration":590,"Attr":{"Baggage":null,"CabinBaggage":null},"stop_over":""},{"Origin":{"AirportCode":"NDJ","CityName":"Ndjamena","AirportName":"Ndjamena","DateTime":"2022-04-13 14:25","FDTV":1649580900},"Destination":{"AirportCode":"ADD","CityName":"Addis Ababa","AirportName":"Addis Ababa","DateTime":"2022-04-13 20:25","FATV":1649602500},"OperatorCode":"ET","DisplayOperatorCode":"","ValidatingAirline":"","OperatorName":"Ethiopian airlines","FlightNumber":"938","CabinClass":"ECONOMY","Operatedbyairline":null,"Operatedbyairlinename":null,"Duration":590,"Attr":{"Baggage":null,"CabinBaggage":null},"stop_over":""},{"Origin":{"AirportCode":"ADD","CityName":"Addis Ababa","AirportName":"Addis Ababa","DateTime":"2022-04-14 09:00","FDTV":1649561400},"Destination":{"AirportCode":"NSI","CityName":"Yaounde","AirportName":"Yaounde","DateTime":"2022-04-14 11:00","FATV":1649568600},"OperatorCode":"ET","DisplayOperatorCode":"","ValidatingAirline":"","OperatorName":"Ethiopian airlines","FlightNumber":"945","CabinClass":"ECONOMY","Operatedbyairline":null,"Operatedbyairlinename":null,"Duration":590,"Attr":{"Baggage":null,"CabinBaggage":null},"stop_over":""}]]},"Price":{"Currency":"USD","TotalDisplayFare":1292.842,"PriceBreakup":{"BasicFare":438.2,"Tax":854.641,"AgentCommission":0,"AgentTdsOnCommision":0},"PassengerBreakup":{"ADT":{"BasePrice":438.2,"Tax":854.641,"TotalPrice":1292.842,"PassengerCount":"1"}}},"Attr":{"IsRefundable":"","AirlineRemark":"","API":"PK Fare"},"ResultToken":"27b0e98990e0ccca132dedd064973ac6*_*9*_*iuvredpYQl06DWPl","api_original_price_details":{"TotalDisplayFare":1292.842,"api_currency":"USD","AgentCommission":0,"BasicFare":438.2,"Tax":854.641},"FareDetails":{"Currency":"EUR","BaseFare":398.76,"Tax":777.72,"PublishedFare":1176.49,"AgentCommission":0,"AgentTdsOnCommision":0,"OfferedFare":1176.49},"PassengerFareBreakdown":{"ADT":{"Tax":854.641,"TotalPrice":1292.842,"PassengerCount":"1","BaseFare":398.76}}}}